emailsender_rht/__init__.py
emailsender_rht/main.py
emailsender_rht/setup.py
email_sender_rht-0.0.1.dist-info/LICENSE
email_sender_rht-0.0.1.dist-info/METADATA
email_sender_rht-0.0.1.dist-info/WHEEL
email_sender_rht-0.0.1.dist-info/top_level.txt
email_sender_rht-0.0.1.dist-info/RECORD
