Metadata-Version: 2.1
Name: email-sender-rht
Version: 0.0.1
Summary: This package makes it easy to send emails to people.
Author-email: Rostel High Tech <rostelhightech@gmail.com>
Project-URL: Homepage, https://github.com/rostelhightech/emailSenderRHT
Classifier: Programming Language :: Python :: 3
Classifier: License :: OSI Approved :: MIT License
Classifier: Operating System :: OS Independent
Requires-Python: >=3.8
License-File: LICENSE
